be_proxy_ip/__about__.py
be_proxy_ip/__init__.py
be_proxy_ip/proxy_ip.py
be_proxy_ip-1.2.0.dist-info/LICENSE
be_proxy_ip-1.2.0.dist-info/METADATA
be_proxy_ip-1.2.0.dist-info/WHEEL
be_proxy_ip-1.2.0.dist-info/top_level.txt
be_proxy_ip-1.2.0.dist-info/RECORD
